[
  {
    "id": "recipe_1",
    "slug": "paneer-butter-masala",
    "title": "Paneer Butter Masala",
    "category": "Desserts",
    "cuisine": "Thai",
    "difficulty": "Easy",
    "time": 135,
    "thumbnail": "https://images.unsplash.com/photo-1546069901-ba9599a7e63c?q=80&w=400&auto=format&fit=crop",
    "rating": 3.7
  },
  {
    "id": "recipe_2",
    "slug": "chicken-tikka-masala",
    "title": "Chicken Tikka Masala",
    "category": "Festival Recipes",
    "cuisine": "Italian",
    "difficulty": "Hard",
    "time": 60,
    "thumbnail": "https://images.unsplash.com/photo-1546069901-ba9599a7e63c?q=80&w=400&auto=format&fit=crop",
    "rating": 4.1
  },
  {
    "id": "recipe_3",
    "slug": "margherita-pizza",
    "title": "Margherita Pizza",
    "category": "Breakfast",
    "cuisine": "Italian",
    "difficulty": "Hard",
    "time": 55,
    "thumbnail": "https://images.unsplash.com/photo-1546069901-ba9599a7e63c?q=80&w=400&auto=format&fit=crop",
    "rating": 4
  },
  {
    "id": "recipe_4",
    "slug": "spaghetti-carbonara",
    "title": "Spaghetti Carbonara",
    "category": "Festival Recipes",
    "cuisine": "Chinese",
    "difficulty": "Easy",
    "time": 95,
    "thumbnail": "https://images.unsplash.com/photo-1546069901-ba9599a7e63c?q=80&w=400&auto=format&fit=crop",
    "rating": 4.4
  },
  {
    "id": "recipe_5",
    "slug": "pad-thai",
    "title": "Pad Thai",
    "category": "Healthy Recipes",
    "cuisine": "Italian",
    "difficulty": "Easy",
    "time": 95,
    "thumbnail": "https://images.unsplash.com/photo-1546069901-ba9599a7e63c?q=80&w=400&auto=format&fit=crop",
    "rating": 4
  },
  {
    "id": "recipe_6",
    "slug": "sushi-rolls",
    "title": "Sushi Rolls",
    "category": "Healthy Recipes",
    "cuisine": "Thai",
    "difficulty": "Easy",
    "time": 129,
    "thumbnail": "https://images.unsplash.com/photo-1546069901-ba9599a7e63c?q=80&w=400&auto=format&fit=crop",
    "rating": 4.9
  },
  {
    "id": "recipe_7",
    "slug": "tacos-al-pastor",
    "title": "Tacos al Pastor",
    "category": "Desserts",
    "cuisine": "Thai",
    "difficulty": "Medium",
    "time": 100,
    "thumbnail": "https://images.unsplash.com/photo-1546069901-ba9599a7e63c?q=80&w=400&auto=format&fit=crop",
    "rating": 4.3
  },
  {
    "id": "recipe_8",
    "slug": "chocolate-lava-cake",
    "title": "Chocolate Lava Cake",
    "category": "Lunch",
    "cuisine": "Indian",
    "difficulty": "Easy",
    "time": 64,
    "thumbnail": "https://images.unsplash.com/photo-1546069901-ba9599a7e63c?q=80&w=400&auto=format&fit=crop",
    "rating": 4.9
  },
  {
    "id": "recipe_9",
    "slug": "caesar-salad",
    "title": "Caesar Salad",
    "category": "Festival Recipes",
    "cuisine": "Italian",
    "difficulty": "Medium",
    "time": 84,
    "thumbnail": "https://images.unsplash.com/photo-1546069901-ba9599a7e63c?q=80&w=400&auto=format&fit=crop",
    "rating": 3.9
  },
  {
    "id": "recipe_10",
    "slug": "greek-salad",
    "title": "Greek Salad",
    "category": "Seasonal Recipes",
    "cuisine": "Japanese",
    "difficulty": "Medium",
    "time": 46,
    "thumbnail": "https://images.unsplash.com/photo-1546069901-ba9599a7e63c?q=80&w=400&auto=format&fit=crop",
    "rating": 3.8
  },
  {
    "id": "recipe_11",
    "slug": "dal-makhani",
    "title": "Dal Makhani",
    "category": "Lunch",
    "cuisine": "Mexican",
    "difficulty": "Hard",
    "time": 94,
    "thumbnail": "https://images.unsplash.com/photo-1546069901-ba9599a7e63c?q=80&w=400&auto=format&fit=crop",
    "rating": 3.7
  },
  {
    "id": "recipe_12",
    "slug": "chole-bhature",
    "title": "Chole Bhature",
    "category": "Festival Recipes",
    "cuisine": "Chinese",
    "difficulty": "Hard",
    "time": 131,
    "thumbnail": "https://images.unsplash.com/photo-1546069901-ba9599a7e63c?q=80&w=400&auto=format&fit=crop",
    "rating": 4.3
  },
  {
    "id": "recipe_13",
    "slug": "palak-paneer",
    "title": "Palak Paneer",
    "category": "Lunch",
    "cuisine": "Chinese",
    "difficulty": "Medium",
    "time": 152,
    "thumbnail": "https://images.unsplash.com/photo-1546069901-ba9599a7e63c?q=80&w=400&auto=format&fit=crop",
    "rating": 3.9
  },
  {
    "id": "recipe_14",
    "slug": "biryani",
    "title": "Biryani",
    "category": "Lunch",
    "cuisine": "American",
    "difficulty": "Medium",
    "time": 60,
    "thumbnail": "https://images.unsplash.com/photo-1546069901-ba9599a7e63c?q=80&w=400&auto=format&fit=crop",
    "rating": 3.9
  },
  {
    "id": "recipe_15",
    "slug": "masala-dosa",
    "title": "Masala Dosa",
    "category": "Desserts",
    "cuisine": "Mexican",
    "difficulty": "Medium",
    "time": 96,
    "thumbnail": "https://images.unsplash.com/photo-1546069901-ba9599a7e63c?q=80&w=400&auto=format&fit=crop",
    "rating": 4.7
  },
  {
    "id": "recipe_16",
    "slug": "idli-sambar",
    "title": "Idli Sambar",
    "category": "Seasonal Recipes",
    "cuisine": "American",
    "difficulty": "Medium",
    "time": 78,
    "thumbnail": "https://images.unsplash.com/photo-1546069901-ba9599a7e63c?q=80&w=400&auto=format&fit=crop",
    "rating": 4.6
  },
  {
    "id": "recipe_17",
    "slug": "butter-chicken",
    "title": "Butter Chicken",
    "category": "Snacks",
    "cuisine": "Italian",
    "difficulty": "Hard",
    "time": 52,
    "thumbnail": "https://images.unsplash.com/photo-1546069901-ba9599a7e63c?q=80&w=400&auto=format&fit=crop",
    "rating": 4.5
  },
  {
    "id": "recipe_18",
    "slug": "rogan-josh",
    "title": "Rogan Josh",
    "category": "Quick Recipes",
    "cuisine": "Indian",
    "difficulty": "Easy",
    "time": 162,
    "thumbnail": "https://images.unsplash.com/photo-1546069901-ba9599a7e63c?q=80&w=400&auto=format&fit=crop",
    "rating": 4.5
  },
  {
    "id": "recipe_19",
    "slug": "mutton-biryani",
    "title": "Mutton Biryani",
    "category": "Desserts",
    "cuisine": "Italian",
    "difficulty": "Medium",
    "time": 122,
    "thumbnail": "https://images.unsplash.com/photo-1546069901-ba9599a7e63c?q=80&w=400&auto=format&fit=crop",
    "rating": 5
  },
  {
    "id": "recipe_20",
    "slug": "fish-curry",
    "title": "Fish Curry",
    "category": "Dinner",
    "cuisine": "Thai",
    "difficulty": "Hard",
    "time": 132,
    "thumbnail": "https://images.unsplash.com/photo-1546069901-ba9599a7e63c?q=80&w=400&auto=format&fit=crop",
    "rating": 4.7
  },
  {
    "id": "recipe_21",
    "slug": "prawn-masala",
    "title": "Prawn Masala",
    "category": "Healthy Recipes",
    "cuisine": "Italian",
    "difficulty": "Easy",
    "time": 35,
    "thumbnail": "https://images.unsplash.com/photo-1546069901-ba9599a7e63c?q=80&w=400&auto=format&fit=crop",
    "rating": 4
  },
  {
    "id": "recipe_22",
    "slug": "egg-curry",
    "title": "Egg Curry",
    "category": "Breakfast",
    "cuisine": "Indian",
    "difficulty": "Medium",
    "time": 133,
    "thumbnail": "https://images.unsplash.com/photo-1546069901-ba9599a7e63c?q=80&w=400&auto=format&fit=crop",
    "rating": 4.8
  },
  {
    "id": "recipe_23",
    "slug": "aloo-gobi",
    "title": "Aloo Gobi",
    "category": "Healthy Recipes",
    "cuisine": "Indian",
    "difficulty": "Medium",
    "time": 66,
    "thumbnail": "https://images.unsplash.com/photo-1546069901-ba9599a7e63c?q=80&w=400&auto=format&fit=crop",
    "rating": 5
  },
  {
    "id": "recipe_24",
    "slug": "bhindi-masala",
    "title": "Bhindi Masala",
    "category": "Dinner",
    "cuisine": "American",
    "difficulty": "Medium",
    "time": 93,
    "thumbnail": "https://images.unsplash.com/photo-1546069901-ba9599a7e63c?q=80&w=400&auto=format&fit=crop",
    "rating": 3.5
  },
  {
    "id": "recipe_25",
    "slug": "baingan-bharta",
    "title": "Baingan Bharta",
    "category": "Festival Recipes",
    "cuisine": "Mexican",
    "difficulty": "Easy",
    "time": 143,
    "thumbnail": "https://images.unsplash.com/photo-1546069901-ba9599a7e63c?q=80&w=400&auto=format&fit=crop",
    "rating": 4.7
  },
  {
    "id": "recipe_26",
    "slug": "malai-kofta",
    "title": "Malai Kofta",
    "category": "Breakfast",
    "cuisine": "Mexican",
    "difficulty": "Easy",
    "time": 86,
    "thumbnail": "https://images.unsplash.com/photo-1546069901-ba9599a7e63c?q=80&w=400&auto=format&fit=crop",
    "rating": 4.5
  },
  {
    "id": "recipe_27",
    "slug": "kadai-paneer",
    "title": "Kadai Paneer",
    "category": "Seasonal Recipes",
    "cuisine": "Indian",
    "difficulty": "Easy",
    "time": 97,
    "thumbnail": "https://images.unsplash.com/photo-1546069901-ba9599a7e63c?q=80&w=400&auto=format&fit=crop",
    "rating": 4
  },
  {
    "id": "recipe_28",
    "slug": "matar-paneer",
    "title": "Matar Paneer",
    "category": "Drinks",
    "cuisine": "Japanese",
    "difficulty": "Easy",
    "time": 101,
    "thumbnail": "https://images.unsplash.com/photo-1546069901-ba9599a7e63c?q=80&w=400&auto=format&fit=crop",
    "rating": 4.5
  },
  {
    "id": "recipe_29",
    "slug": "shahi-tukda",
    "title": "Shahi Tukda",
    "category": "Breakfast",
    "cuisine": "Chinese",
    "difficulty": "Easy",
    "time": 111,
    "thumbnail": "https://images.unsplash.com/photo-1546069901-ba9599a7e63c?q=80&w=400&auto=format&fit=crop",
    "rating": 3.5
  },
  {
    "id": "recipe_30",
    "slug": "gulab-jamun",
    "title": "Gulab Jamun",
    "category": "Desserts",
    "cuisine": "Japanese",
    "difficulty": "Medium",
    "time": 56,
    "thumbnail": "https://images.unsplash.com/photo-1546069901-ba9599a7e63c?q=80&w=400&auto=format&fit=crop",
    "rating": 4.6
  },
  {
    "id": "recipe_31",
    "slug": "rasgulla",
    "title": "Rasgulla",
    "category": "Desserts",
    "cuisine": "Indian",
    "difficulty": "Easy",
    "time": 140,
    "thumbnail": "https://images.unsplash.com/photo-1546069901-ba9599a7e63c?q=80&w=400&auto=format&fit=crop",
    "rating": 4.3
  },
  {
    "id": "recipe_32",
    "slug": "jalebi",
    "title": "Jalebi",
    "category": "Snacks",
    "cuisine": "Italian",
    "difficulty": "Medium",
    "time": 61,
    "thumbnail": "https://images.unsplash.com/photo-1546069901-ba9599a7e63c?q=80&w=400&auto=format&fit=crop",
    "rating": 4.3
  },
  {
    "id": "recipe_33",
    "slug": "gajar-ka-halwa",
    "title": "Gajar Ka Halwa",
    "category": "Quick Recipes",
    "cuisine": "Mexican",
    "difficulty": "Easy",
    "time": 94,
    "thumbnail": "https://images.unsplash.com/photo-1546069901-ba9599a7e63c?q=80&w=400&auto=format&fit=crop",
    "rating": 4.6
  },
  {
    "id": "recipe_34",
    "slug": "kheer",
    "title": "Kheer",
    "category": "Snacks",
    "cuisine": "Chinese",
    "difficulty": "Medium",
    "time": 64,
    "thumbnail": "https://images.unsplash.com/photo-1546069901-ba9599a7e63c?q=80&w=400&auto=format&fit=crop",
    "rating": 3.5
  },
  {
    "id": "recipe_35",
    "slug": "lassi",
    "title": "Lassi",
    "category": "Seasonal Recipes",
    "cuisine": "Japanese",
    "difficulty": "Medium",
    "time": 57,
    "thumbnail": "https://images.unsplash.com/photo-1546069901-ba9599a7e63c?q=80&w=400&auto=format&fit=crop",
    "rating": 5
  },
  {
    "id": "recipe_36",
    "slug": "mango-lassi",
    "title": "Mango Lassi",
    "category": "Breakfast",
    "cuisine": "Italian",
    "difficulty": "Medium",
    "time": 91,
    "thumbnail": "https://images.unsplash.com/photo-1546069901-ba9599a7e63c?q=80&w=400&auto=format&fit=crop",
    "rating": 4.4
  },
  {
    "id": "recipe_37",
    "slug": "masala-chai",
    "title": "Masala Chai",
    "category": "Festival Recipes",
    "cuisine": "Japanese",
    "difficulty": "Medium",
    "time": 58,
    "thumbnail": "https://images.unsplash.com/photo-1546069901-ba9599a7e63c?q=80&w=400&auto=format&fit=crop",
    "rating": 4.3
  },
  {
    "id": "recipe_38",
    "slug": "cold-coffee",
    "title": "Cold Coffee",
    "category": "Breakfast",
    "cuisine": "Italian",
    "difficulty": "Medium",
    "time": 45,
    "thumbnail": "https://images.unsplash.com/photo-1546069901-ba9599a7e63c?q=80&w=400&auto=format&fit=crop",
    "rating": 3.8
  },
  {
    "id": "recipe_39",
    "slug": "mojito",
    "title": "Mojito",
    "category": "Healthy Recipes",
    "cuisine": "Italian",
    "difficulty": "Hard",
    "time": 115,
    "thumbnail": "https://images.unsplash.com/photo-1546069901-ba9599a7e63c?q=80&w=400&auto=format&fit=crop",
    "rating": 3.5
  },
  {
    "id": "recipe_40",
    "slug": "lemonade",
    "title": "Lemonade",
    "category": "Snacks",
    "cuisine": "Thai",
    "difficulty": "Medium",
    "time": 104,
    "thumbnail": "https://images.unsplash.com/photo-1546069901-ba9599a7e63c?q=80&w=400&auto=format&fit=crop",
    "rating": 3.7
  },
  {
    "id": "recipe_41",
    "slug": "pancakes",
    "title": "Pancakes",
    "category": "Drinks",
    "cuisine": "Italian",
    "difficulty": "Easy",
    "time": 28,
    "thumbnail": "https://images.unsplash.com/photo-1546069901-ba9599a7e63c?q=80&w=400&auto=format&fit=crop",
    "rating": 3.6
  },
  {
    "id": "recipe_42",
    "slug": "waffles",
    "title": "Waffles",
    "category": "Lunch",
    "cuisine": "Japanese",
    "difficulty": "Hard",
    "time": 144,
    "thumbnail": "https://images.unsplash.com/photo-1546069901-ba9599a7e63c?q=80&w=400&auto=format&fit=crop",
    "rating": 4.5
  },
  {
    "id": "recipe_43",
    "slug": "french-toast",
    "title": "French Toast",
    "category": "Dinner",
    "cuisine": "Japanese",
    "difficulty": "Easy",
    "time": 63,
    "thumbnail": "https://images.unsplash.com/photo-1546069901-ba9599a7e63c?q=80&w=400&auto=format&fit=crop",
    "rating": 4.2
  },
  {
    "id": "recipe_44",
    "slug": "omelette",
    "title": "Omelette",
    "category": "Quick Recipes",
    "cuisine": "Chinese",
    "difficulty": "Medium",
    "time": 132,
    "thumbnail": "https://images.unsplash.com/photo-1546069901-ba9599a7e63c?q=80&w=400&auto=format&fit=crop",
    "rating": 4
  },
  {
    "id": "recipe_45",
    "slug": "scrambled-eggs",
    "title": "Scrambled Eggs",
    "category": "Festival Recipes",
    "cuisine": "Italian",
    "difficulty": "Easy",
    "time": 144,
    "thumbnail": "https://images.unsplash.com/photo-1546069901-ba9599a7e63c?q=80&w=400&auto=format&fit=crop",
    "rating": 3.8
  },
  {
    "id": "recipe_46",
    "slug": "avocado-toast",
    "title": "Avocado Toast",
    "category": "Lunch",
    "cuisine": "Chinese",
    "difficulty": "Medium",
    "time": 92,
    "thumbnail": "https://images.unsplash.com/photo-1546069901-ba9599a7e63c?q=80&w=400&auto=format&fit=crop",
    "rating": 4.4
  },
  {
    "id": "recipe_47",
    "slug": "oatmeal",
    "title": "Oatmeal",
    "category": "Healthy Recipes",
    "cuisine": "Japanese",
    "difficulty": "Medium",
    "time": 157,
    "thumbnail": "https://images.unsplash.com/photo-1546069901-ba9599a7e63c?q=80&w=400&auto=format&fit=crop",
    "rating": 3.7
  },
  {
    "id": "recipe_48",
    "slug": "smoothie-bowl",
    "title": "Smoothie Bowl",
    "category": "Seasonal Recipes",
    "cuisine": "Japanese",
    "difficulty": "Easy",
    "time": 84,
    "thumbnail": "https://images.unsplash.com/photo-1546069901-ba9599a7e63c?q=80&w=400&auto=format&fit=crop",
    "rating": 4.2
  },
  {
    "id": "recipe_49",
    "slug": "burger",
    "title": "Burger",
    "category": "Dinner",
    "cuisine": "Italian",
    "difficulty": "Medium",
    "time": 120,
    "thumbnail": "https://images.unsplash.com/photo-1546069901-ba9599a7e63c?q=80&w=400&auto=format&fit=crop",
    "rating": 3.7
  },
  {
    "id": "recipe_50",
    "slug": "sandwich",
    "title": "Sandwich",
    "category": "Festival Recipes",
    "cuisine": "American",
    "difficulty": "Hard",
    "time": 101,
    "thumbnail": "https://images.unsplash.com/photo-1546069901-ba9599a7e63c?q=80&w=400&auto=format&fit=crop",
    "rating": 4
  },
  {
    "id": "recipe_51",
    "slug": "wrap",
    "title": "Wrap",
    "category": "Festival Recipes",
    "cuisine": "Mexican",
    "difficulty": "Medium",
    "time": 65,
    "thumbnail": "https://images.unsplash.com/photo-1546069901-ba9599a7e63c?q=80&w=400&auto=format&fit=crop",
    "rating": 4.5
  },
  {
    "id": "recipe_52",
    "slug": "shawarma",
    "title": "Shawarma",
    "category": "Healthy Recipes",
    "cuisine": "Thai",
    "difficulty": "Hard",
    "time": 122,
    "thumbnail": "https://images.unsplash.com/photo-1546069901-ba9599a7e63c?q=80&w=400&auto=format&fit=crop",
    "rating": 4.6
  },
  {
    "id": "recipe_53",
    "slug": "falafel",
    "title": "Falafel",
    "category": "Quick Recipes",
    "cuisine": "American",
    "difficulty": "Easy",
    "time": 60,
    "thumbnail": "https://images.unsplash.com/photo-1546069901-ba9599a7e63c?q=80&w=400&auto=format&fit=crop",
    "rating": 3.6
  },
  {
    "id": "recipe_54",
    "slug": "hummus",
    "title": "Hummus",
    "category": "Seasonal Recipes",
    "cuisine": "American",
    "difficulty": "Easy",
    "time": 115,
    "thumbnail": "https://images.unsplash.com/photo-1546069901-ba9599a7e63c?q=80&w=400&auto=format&fit=crop",
    "rating": 4
  },
  {
    "id": "recipe_55",
    "slug": "pita-bread",
    "title": "Pita Bread",
    "category": "Lunch",
    "cuisine": "American",
    "difficulty": "Hard",
    "time": 61,
    "thumbnail": "https://images.unsplash.com/photo-1546069901-ba9599a7e63c?q=80&w=400&auto=format&fit=crop",
    "rating": 4.7
  },
  {
    "id": "recipe_56",
    "slug": "garlic-bread",
    "title": "Garlic Bread",
    "category": "Quick Recipes",
    "cuisine": "Italian",
    "difficulty": "Easy",
    "time": 104,
    "thumbnail": "https://images.unsplash.com/photo-1546069901-ba9599a7e63c?q=80&w=400&auto=format&fit=crop",
    "rating": 4.9
  },
  {
    "id": "recipe_57",
    "slug": "bruschetta",
    "title": "Bruschetta",
    "category": "Quick Recipes",
    "cuisine": "Italian",
    "difficulty": "Easy",
    "time": 61,
    "thumbnail": "https://images.unsplash.com/photo-1546069901-ba9599a7e63c?q=80&w=400&auto=format&fit=crop",
    "rating": 3.8
  },
  {
    "id": "recipe_58",
    "slug": "spring-rolls",
    "title": "Spring Rolls",
    "category": "Seasonal Recipes",
    "cuisine": "Thai",
    "difficulty": "Medium",
    "time": 97,
    "thumbnail": "https://images.unsplash.com/photo-1546069901-ba9599a7e63c?q=80&w=400&auto=format&fit=crop",
    "rating": 3.6
  },
  {
    "id": "recipe_59",
    "slug": "dumplings",
    "title": "Dumplings",
    "category": "Healthy Recipes",
    "cuisine": "Chinese",
    "difficulty": "Hard",
    "time": 78,
    "thumbnail": "https://images.unsplash.com/photo-1546069901-ba9599a7e63c?q=80&w=400&auto=format&fit=crop",
    "rating": 4.8
  },
  {
    "id": "recipe_60",
    "slug": "noodles",
    "title": "Noodles",
    "category": "Dinner",
    "cuisine": "Mexican",
    "difficulty": "Medium",
    "time": 87,
    "thumbnail": "https://images.unsplash.com/photo-1546069901-ba9599a7e63c?q=80&w=400&auto=format&fit=crop",
    "rating": 3.8
  },
  {
    "id": "recipe_61",
    "slug": "fried-rice",
    "title": "Fried Rice",
    "category": "Desserts",
    "cuisine": "American",
    "difficulty": "Medium",
    "time": 77,
    "thumbnail": "https://images.unsplash.com/photo-1546069901-ba9599a7e63c?q=80&w=400&auto=format&fit=crop",
    "rating": 4.1
  },
  {
    "id": "recipe_62",
    "slug": "manchurian",
    "title": "Manchurian",
    "category": "Desserts",
    "cuisine": "Italian",
    "difficulty": "Medium",
    "time": 159,
    "thumbnail": "https://images.unsplash.com/photo-1546069901-ba9599a7e63c?q=80&w=400&auto=format&fit=crop",
    "rating": 4.1
  },
  {
    "id": "recipe_63",
    "slug": "chilli-chicken",
    "title": "Chilli Chicken",
    "category": "Quick Recipes",
    "cuisine": "Chinese",
    "difficulty": "Medium",
    "time": 40,
    "thumbnail": "https://images.unsplash.com/photo-1546069901-ba9599a7e63c?q=80&w=400&auto=format&fit=crop",
    "rating": 3.9
  },
  {
    "id": "recipe_64",
    "slug": "chicken-65",
    "title": "Chicken 65",
    "category": "Festival Recipes",
    "cuisine": "Mexican",
    "difficulty": "Hard",
    "time": 103,
    "thumbnail": "https://images.unsplash.com/photo-1546069901-ba9599a7e63c?q=80&w=400&auto=format&fit=crop",
    "rating": 4.4
  },
  {
    "id": "recipe_65",
    "slug": "tandoori-chicken",
    "title": "Tandoori Chicken",
    "category": "Drinks",
    "cuisine": "Chinese",
    "difficulty": "Medium",
    "time": 59,
    "thumbnail": "https://images.unsplash.com/photo-1546069901-ba9599a7e63c?q=80&w=400&auto=format&fit=crop",
    "rating": 3.7
  },
  {
    "id": "recipe_66",
    "slug": "seekh-kebab",
    "title": "Seekh Kebab",
    "category": "Seasonal Recipes",
    "cuisine": "Italian",
    "difficulty": "Hard",
    "time": 154,
    "thumbnail": "https://images.unsplash.com/photo-1546069901-ba9599a7e63c?q=80&w=400&auto=format&fit=crop",
    "rating": 4.2
  },
  {
    "id": "recipe_67",
    "slug": "reshmi-kebab",
    "title": "Reshmi Kebab",
    "category": "Lunch",
    "cuisine": "Indian",
    "difficulty": "Medium",
    "time": 63,
    "thumbnail": "https://images.unsplash.com/photo-1546069901-ba9599a7e63c?q=80&w=400&auto=format&fit=crop",
    "rating": 3.9
  },
  {
    "id": "recipe_68",
    "slug": "boti-kebab",
    "title": "Boti Kebab",
    "category": "Desserts",
    "cuisine": "Chinese",
    "difficulty": "Medium",
    "time": 60,
    "thumbnail": "https://images.unsplash.com/photo-1546069901-ba9599a7e63c?q=80&w=400&auto=format&fit=crop",
    "rating": 3.6
  },
  {
    "id": "recipe_69",
    "slug": "kathi-roll",
    "title": "Kathi Roll",
    "category": "Desserts",
    "cuisine": "Mexican",
    "difficulty": "Easy",
    "time": 96,
    "thumbnail": "https://images.unsplash.com/photo-1546069901-ba9599a7e63c?q=80&w=400&auto=format&fit=crop",
    "rating": 4.2
  },
  {
    "id": "recipe_70",
    "slug": "pav-bhaji",
    "title": "Pav Bhaji",
    "category": "Snacks",
    "cuisine": "Thai",
    "difficulty": "Medium",
    "time": 135,
    "thumbnail": "https://images.unsplash.com/photo-1546069901-ba9599a7e63c?q=80&w=400&auto=format&fit=crop",
    "rating": 3.7
  },
  {
    "id": "recipe_71",
    "slug": "vada-pav",
    "title": "Vada Pav",
    "category": "Healthy Recipes",
    "cuisine": "Chinese",
    "difficulty": "Hard",
    "time": 144,
    "thumbnail": "https://images.unsplash.com/photo-1546069901-ba9599a7e63c?q=80&w=400&auto=format&fit=crop",
    "rating": 3.7
  },
  {
    "id": "recipe_72",
    "slug": "misal-pav",
    "title": "Misal Pav",
    "category": "Lunch",
    "cuisine": "Thai",
    "difficulty": "Easy",
    "time": 119,
    "thumbnail": "https://images.unsplash.com/photo-1546069901-ba9599a7e63c?q=80&w=400&auto=format&fit=crop",
    "rating": 3.8
  },
  {
    "id": "recipe_73",
    "slug": "pani-puri",
    "title": "Pani Puri",
    "category": "Quick Recipes",
    "cuisine": "Japanese",
    "difficulty": "Hard",
    "time": 47,
    "thumbnail": "https://images.unsplash.com/photo-1546069901-ba9599a7e63c?q=80&w=400&auto=format&fit=crop",
    "rating": 3.6
  },
  {
    "id": "recipe_74",
    "slug": "bhel-puri",
    "title": "Bhel Puri",
    "category": "Seasonal Recipes",
    "cuisine": "Chinese",
    "difficulty": "Easy",
    "time": 139,
    "thumbnail": "https://images.unsplash.com/photo-1546069901-ba9599a7e63c?q=80&w=400&auto=format&fit=crop",
    "rating": 4.2
  },
  {
    "id": "recipe_75",
    "slug": "sev-puri",
    "title": "Sev Puri",
    "category": "Festival Recipes",
    "cuisine": "Japanese",
    "difficulty": "Easy",
    "time": 133,
    "thumbnail": "https://images.unsplash.com/photo-1546069901-ba9599a7e63c?q=80&w=400&auto=format&fit=crop",
    "rating": 4.5
  },
  {
    "id": "recipe_76",
    "slug": "dahi-puri",
    "title": "Dahi Puri",
    "category": "Healthy Recipes",
    "cuisine": "Italian",
    "difficulty": "Medium",
    "time": 92,
    "thumbnail": "https://images.unsplash.com/photo-1546069901-ba9599a7e63c?q=80&w=400&auto=format&fit=crop",
    "rating": 3.7
  },
  {
    "id": "recipe_77",
    "slug": "aloo-tikki",
    "title": "Aloo Tikki",
    "category": "Lunch",
    "cuisine": "Thai",
    "difficulty": "Easy",
    "time": 83,
    "thumbnail": "https://images.unsplash.com/photo-1546069901-ba9599a7e63c?q=80&w=400&auto=format&fit=crop",
    "rating": 4
  },
  {
    "id": "recipe_78",
    "slug": "samosa",
    "title": "Samosa",
    "category": "Quick Recipes",
    "cuisine": "Japanese",
    "difficulty": "Hard",
    "time": 134,
    "thumbnail": "https://images.unsplash.com/photo-1546069901-ba9599a7e63c?q=80&w=400&auto=format&fit=crop",
    "rating": 3.6
  },
  {
    "id": "recipe_79",
    "slug": "kachori",
    "title": "Kachori",
    "category": "Healthy Recipes",
    "cuisine": "Thai",
    "difficulty": "Easy",
    "time": 154,
    "thumbnail": "https://images.unsplash.com/photo-1546069901-ba9599a7e63c?q=80&w=400&auto=format&fit=crop",
    "rating": 4.1
  },
  {
    "id": "recipe_80",
    "slug": "pakora",
    "title": "Pakora",
    "category": "Desserts",
    "cuisine": "American",
    "difficulty": "Medium",
    "time": 117,
    "thumbnail": "https://images.unsplash.com/photo-1546069901-ba9599a7e63c?q=80&w=400&auto=format&fit=crop",
    "rating": 3.9
  },
  {
    "id": "recipe_81",
    "slug": "dhokla",
    "title": "Dhokla",
    "category": "Desserts",
    "cuisine": "Italian",
    "difficulty": "Medium",
    "time": 62,
    "thumbnail": "https://images.unsplash.com/photo-1546069901-ba9599a7e63c?q=80&w=400&auto=format&fit=crop",
    "rating": 3.7
  },
  {
    "id": "recipe_82",
    "slug": "khandvi",
    "title": "Khandvi",
    "category": "Dinner",
    "cuisine": "Thai",
    "difficulty": "Hard",
    "time": 61,
    "thumbnail": "https://images.unsplash.com/photo-1546069901-ba9599a7e63c?q=80&w=400&auto=format&fit=crop",
    "rating": 4.4
  },
  {
    "id": "recipe_83",
    "slug": "thepla",
    "title": "Thepla",
    "category": "Lunch",
    "cuisine": "Italian",
    "difficulty": "Medium",
    "time": 132,
    "thumbnail": "https://images.unsplash.com/photo-1546069901-ba9599a7e63c?q=80&w=400&auto=format&fit=crop",
    "rating": 4.1
  },
  {
    "id": "recipe_84",
    "slug": "fafda",
    "title": "Fafda",
    "category": "Snacks",
    "cuisine": "Chinese",
    "difficulty": "Hard",
    "time": 116,
    "thumbnail": "https://images.unsplash.com/photo-1546069901-ba9599a7e63c?q=80&w=400&auto=format&fit=crop",
    "rating": 4
  },
  {
    "id": "recipe_85",
    "slug": "poha",
    "title": "Poha",
    "category": "Drinks",
    "cuisine": "Indian",
    "difficulty": "Easy",
    "time": 65,
    "thumbnail": "https://images.unsplash.com/photo-1546069901-ba9599a7e63c?q=80&w=400&auto=format&fit=crop",
    "rating": 4.3
  },
  {
    "id": "recipe_86",
    "slug": "upma",
    "title": "Upma",
    "category": "Desserts",
    "cuisine": "Chinese",
    "difficulty": "Hard",
    "time": 97,
    "thumbnail": "https://images.unsplash.com/photo-1546069901-ba9599a7e63c?q=80&w=400&auto=format&fit=crop",
    "rating": 4.3
  },
  {
    "id": "recipe_87",
    "slug": "uttapam",
    "title": "Uttapam",
    "category": "Festival Recipes",
    "cuisine": "Thai",
    "difficulty": "Easy",
    "time": 75,
    "thumbnail": "https://images.unsplash.com/photo-1546069901-ba9599a7e63c?q=80&w=400&auto=format&fit=crop",
    "rating": 3.5
  },
  {
    "id": "recipe_88",
    "slug": "pongal",
    "title": "Pongal",
    "category": "Quick Recipes",
    "cuisine": "Thai",
    "difficulty": "Easy",
    "time": 155,
    "thumbnail": "https://images.unsplash.com/photo-1546069901-ba9599a7e63c?q=80&w=400&auto=format&fit=crop",
    "rating": 4.1
  },
  {
    "id": "recipe_89",
    "slug": "bisi-bele-bath",
    "title": "Bisi Bele Bath",
    "category": "Lunch",
    "cuisine": "Chinese",
    "difficulty": "Medium",
    "time": 69,
    "thumbnail": "https://images.unsplash.com/photo-1546069901-ba9599a7e63c?q=80&w=400&auto=format&fit=crop",
    "rating": 4.1
  },
  {
    "id": "recipe_90",
    "slug": "pulihora",
    "title": "Pulihora",
    "category": "Lunch",
    "cuisine": "Chinese",
    "difficulty": "Easy",
    "time": 131,
    "thumbnail": "https://images.unsplash.com/photo-1546069901-ba9599a7e63c?q=80&w=400&auto=format&fit=crop",
    "rating": 4.4
  },
  {
    "id": "recipe_91",
    "slug": "lemon-rice",
    "title": "Lemon Rice",
    "category": "Lunch",
    "cuisine": "Japanese",
    "difficulty": "Easy",
    "time": 102,
    "thumbnail": "https://images.unsplash.com/photo-1546069901-ba9599a7e63c?q=80&w=400&auto=format&fit=crop",
    "rating": 4.5
  },
  {
    "id": "recipe_92",
    "slug": "curd-rice",
    "title": "Curd Rice",
    "category": "Dinner",
    "cuisine": "Chinese",
    "difficulty": "Easy",
    "time": 72,
    "thumbnail": "https://images.unsplash.com/photo-1546069901-ba9599a7e63c?q=80&w=400&auto=format&fit=crop",
    "rating": 4.7
  },
  {
    "id": "recipe_93",
    "slug": "tomato-rice",
    "title": "Tomato Rice",
    "category": "Seasonal Recipes",
    "cuisine": "Indian",
    "difficulty": "Hard",
    "time": 89,
    "thumbnail": "https://images.unsplash.com/photo-1546069901-ba9599a7e63c?q=80&w=400&auto=format&fit=crop",
    "rating": 3.5
  },
  {
    "id": "recipe_94",
    "slug": "coconut-rice",
    "title": "Coconut Rice",
    "category": "Seasonal Recipes",
    "cuisine": "Chinese",
    "difficulty": "Easy",
    "time": 103,
    "thumbnail": "https://images.unsplash.com/photo-1546069901-ba9599a7e63c?q=80&w=400&auto=format&fit=crop",
    "rating": 3.6
  },
  {
    "id": "recipe_95",
    "slug": "tamarind-rice",
    "title": "Tamarind Rice",
    "category": "Lunch",
    "cuisine": "Italian",
    "difficulty": "Easy",
    "time": 35,
    "thumbnail": "https://images.unsplash.com/photo-1546069901-ba9599a7e63c?q=80&w=400&auto=format&fit=crop",
    "rating": 4.1
  },
  {
    "id": "recipe_96",
    "slug": "veg-biryani",
    "title": "Veg Biryani",
    "category": "Desserts",
    "cuisine": "Italian",
    "difficulty": "Easy",
    "time": 125,
    "thumbnail": "https://images.unsplash.com/photo-1546069901-ba9599a7e63c?q=80&w=400&auto=format&fit=crop",
    "rating": 4.3
  },
  {
    "id": "recipe_97",
    "slug": "mushroom-biryani",
    "title": "Mushroom Biryani",
    "category": "Quick Recipes",
    "cuisine": "Indian",
    "difficulty": "Medium",
    "time": 69,
    "thumbnail": "https://images.unsplash.com/photo-1546069901-ba9599a7e63c?q=80&w=400&auto=format&fit=crop",
    "rating": 3.7
  },
  {
    "id": "recipe_98",
    "slug": "paneer-biryani",
    "title": "Paneer Biryani",
    "category": "Breakfast",
    "cuisine": "Italian",
    "difficulty": "Hard",
    "time": 92,
    "thumbnail": "https://images.unsplash.com/photo-1546069901-ba9599a7e63c?q=80&w=400&auto=format&fit=crop",
    "rating": 4.4
  },
  {
    "id": "recipe_99",
    "slug": "chicken-fried-rice",
    "title": "Chicken Fried Rice",
    "category": "Seasonal Recipes",
    "cuisine": "Indian",
    "difficulty": "Easy",
    "time": 25,
    "thumbnail": "https://images.unsplash.com/photo-1546069901-ba9599a7e63c?q=80&w=400&auto=format&fit=crop",
    "rating": 4.5
  },
  {
    "id": "recipe_100",
    "slug": "egg-fried-rice",
    "title": "Egg Fried Rice",
    "category": "Drinks",
    "cuisine": "Italian",
    "difficulty": "Hard",
    "time": 143,
    "thumbnail": "https://images.unsplash.com/photo-1546069901-ba9599a7e63c?q=80&w=400&auto=format&fit=crop",
    "rating": 3.5
  }
]